[
  {
    "seed": "4817190870577053697",
    "shrunk": {
      "x": "[][]int{[]int{0, 1, 2}, []int{3, -1}}"
    }
  },
  {
    "seed": "5116513845879242754",
    "shrunk": {
      "x": "[][]int{[]int{0, 1, 2, 3, 4}}"
    }
  },
  {
    "seed": "5345117831010713604",
    "shrunk": {
      "x": "[][]int{[]int{0, 1, 2, 3, 4}}"
    }
  },
  {
    "seed": "5577910676271136772",
    "shrunk": {
      "x": "[][]int{[]int{0, 1}, []int{2, 3, -1}}"
    }
  },
  {
    "seed": "5868444177095720966",
    "shrunk": {
      "x": "[][]int{[]int{0, 1, 2, 3, 4}}"
    }
  },
  {
    "seed": "6116846050201305095",
    "shrunk": {
      "x": "[][]int{[]int{0, 1}, []int{2, 3, 4}}"
    }
  },
  {
    "seed": "6344370362158940167",
    "shrunk": {
      "x": "[][]int{[]int{0, 1}, []int{2, 3, 4}}"
    }
  },
  {
    "seed": "6522790501999968265",
    "shrunk": {
      "x": "[][]int{[]int{0, 1, 2, 3, -1}}"
    }
  },
  {
    "seed": "6835566968435638281",
    "shrunk": {
      "x": "[][]int{[]int{0, 1, 2, 3, 4}}"
    }
  },
  {
    "seed": "7093820985417138186",
    "shrunk": {
      "x": "[][]int{[]int{0, 1, 2, 3, -1}}"
    }
  },
  {
    "seed": "7301799103074140171",
    "shrunk": {
      "x": "[][]int{[]int{0, 1, 2, 3, 4}}"
    }
  },
  {
    "seed": "7593351902717280268",
    "shrunk": {
      "x": "[][]int{[]int{0, 1, 2, 3, 4}}"
    }
  },
  {
    "seed": "7847359627267145741",
    "shrunk": {
      "x": "[][]int{[]int{0, 1, 2, 3, 4}}"
    }
  },
  {
    "seed": "8176473393382555662",
    "shrunk": {
      "x": "[][]int{[]int{0, 1, 2}, []int{3, -1}}"
    }
  },
  {
    "seed": "8490621736797077520",
    "shrunk": {
      "x": "[][]int{[]int{0}, []int{1, 2, 3}, []int{4}}"
    }
  },
  {
    "seed": "8789652753107386384",
    "shrunk": {
      "x": "[][]int{[]int{0, 1, 2, 3, 4}}"
    }
  },
  {
    "seed": "9010542564658380818",
    "shrunk": {
      "x": "[][]int{[]int{0, 1}, []int{2, 3, 4}}"
    }
  },
  {
    "seed": "9326604406197583890",
    "shrunk": {
      "x": "[][]int{[]int{0, 1, 2, 3, -1}}"
    }
  },
  {
    "seed": "9497687706809925651",
    "shrunk": {
      "x": "[][]int{[]int{0, 1, 2, 3, 4}}"
    }
  },
  {
    "seed": "9752917332375633943",
    "shrunk": {
      "x": "[][]int{[]int{0, 1, 2, 3, 4}}"
    }
  },
  {
    "seed": "10026207591773765653",
    "shrunk": {
      "x": "[][]int{[]int{0, 1, 2, 3, 4}}"
    }
  },
  {
    "seed": "10237044512677429271",
    "shrunk": {
      "x": "[][]int{[]int{0, 1, 2, 3, 4}}"
    }
  },
  {
    "seed": "10442669615321448471",
    "shrunk": {
      "x": "[][]int{[]int{0, 1, 2, 3, 4}}"
    }
  },
  {
    "seed": "10697867062992175128",
    "shrunk": {
      "x": "[][]int{[]int{0, 1, 2, 3, 4}}"
    }
  },
  {
    "seed": "10924707311213608985",
    "shrunk": {
      "x": "[][]int{[]int{0}, []int{1, 2, 3, 4}}"
    }
  },
  {
    "seed": "11176941407543754778",
    "shrunk": {
      "x": "[][]int{[]int{0, 1, 2, 3, 4}}"
    }
  },
  {
    "seed": "11436062587012251675",
    "shrunk": {
      "x": "[][]int{[]int{0, 1, 2, 3, 4}}"
    }
  },
  {
    "seed": "11619185754697105439",
    "shrunk": {
      "x": "[][]int{[]int{0, 1, 2, 3, 4}}"
    }
  },
  {
    "seed": "11861994425037094941",
    "shrunk": {
      "x": "[][]int{[]int{0, 1, 2, 3, -1}}"
    }
  },
  {
    "seed": "12130712850662424606",
    "shrunk": {
      "x": "[][]int{[]int{0, 1, 2, 3, 4}}"
    }
  },
  {
    "seed": "12381342609203789855",
    "shrunk": {
      "x": "[][]int{[]int{0, 1, 2, 3, 4}}"
    }
  },
  {
    "seed": "12690095434312450080",
    "shrunk": {
      "x": "[][]int{[]int{0, 1, 2, 3, 4}}"
    }
  },
  {
    "seed": "12911525947886272545",
    "shrunk": {
      "x": "[][]int{[]int{0, 1, 2, 3, 4}}"
    }
  },
  {
    "seed": "13188778121341435941",
    "shrunk": {
      "x": "[][]int{[]int{0, 1, 2, 3, 4}}"
    }
  },
  {
    "seed": "13425044280884330531",
    "shrunk": {
      "x": "[][]int{[]int{0}, []int{1, 2}, []int{3, 4}}"
    }
  },
  {
    "seed": "13723943467468455973",
    "shrunk": {
      "x": "[][]int{[]int{0, 1, 2, 3}, []int{-1}}"
    }
  },
  {
    "seed": "14018345110329098278",
    "shrunk": {
      "x": "[][]int{[]int{0, 1, 2, 3, 4}}"
    }
  },
  {
    "seed": "14235686690483077158",
    "shrunk": {
      "x": "[][]int{[]int{0, 1, 2, 3, 4}}"
    }
  },
  {
    "seed": "14501571017513631783",
    "shrunk": {
      "x": "[][]int{[]int{0, 1, 2, -1, -2}}"
    }
  },
  {
    "seed": "14722609769940516905",
    "shrunk": {
      "x": "[][]int{[]int{0, 1, 2, 3, 4}}"
    }
  },
  {
    "seed": "14928757986716287018",
    "shrunk": {
      "x": "[][]int{[]int{0, 1, 2, 3, 4}}"
    }
  },
  {
    "seed": "15140457027815342122",
    "shrunk": {
      "x": "[][]int{[]int{0, 1, 2}, []int{3, 4}}"
    }
  },
  {
    "seed": "15457094163043975211",
    "shrunk": {
      "x": "[][]int{[]int{0, 1, 2, 3, 4}}"
    }
  },
  {
    "seed": "15677994578869223469",
    "shrunk": {
      "x": "[][]int{[]int{0, 1, 2, 3, 4}}"
    }
  },
  {
    "seed": "15908858386813288493",
    "shrunk": {
      "x": "[][]int{[]int{0, 1, 2, 3, -1}}"
    }
  },
  {
    "seed": "16146343917636288558",
    "shrunk": {
      "x": "[][]int{[]int{0, 1, 2, 3, 4}}"
    }
  },
  {
    "seed": "16364707867510439983",
    "shrunk": {
      "x": "[][]int{[]int{0, 1, 2, 3, 4}}"
    }
  },
  {
    "seed": "16557528667622735920",
    "shrunk": {
      "x": "[][]int{[]int{0, 1, 2}, []int{3, -1}}"
    }
  },
  {
    "seed": "16856198777831161911",
    "shrunk": {
      "x": "[][]int{[]int{0, 1, 2, 3, 4}}"
    }
  },
  {
    "seed": "17030630039810474034",
    "shrunk": {
      "x": "[][]int{[]int{0, 1, 2, 3, 4}}"
    }
  },
  {
    "seed": "17244029763404693555",
    "shrunk": {
      "x": "[][]int{[]int{0, 1, 2, 3, 4}}"
    }
  },
  {
    "seed": "17483549450868621364",
    "shrunk": {
      "x": "[][]int{[]int{0, 1, 2, 3, 4}}"
    }
  },
  {
    "seed": "17741489389776666680",
    "shrunk": {
      "x": "[][]int{[]int{0, 1, 2, 3, -1}}"
    }
  },
  {
    "seed": "17930753458751668278",
    "shrunk": {
      "x": "[][]int{[]int{0}, []int{1, 2, 3, 4}}"
    }
  },
  {
    "seed": "18218937999012397111",
    "shrunk": {
      "x": "[][]int{[]int{0, 1, 2, 3, 4}}"
    }
  },
  {
    "seed": "30573101926318136",
    "shrunk": {
      "x": "[][]int{[]int{0, 1, 2, 3, 4}}"
    }
  },
  {
    "seed": "270710835184140345",
    "shrunk": {
      "x": "[][]int{[]int{0, 1, 2, 3, 4}}"
    }
  },
  {
    "seed": "552830426356383805",
    "shrunk": {
      "x": "[][]int{[]int{0}, []int{1, 2, 3, 4}}"
    }
  },
  {
    "seed": "847894155605573692",
    "shrunk": {
      "x": "[][]int{[]int{0}, []int{1, 2, 3, 4}}"
    }
  },
  {
    "seed": "1154797095350173756",
    "shrunk": {
      "x": "[][]int{[]int{0, 1, 2, 3, 4}}"
    }
  },
  {
    "seed": "1395983943089520701",
    "shrunk": {
      "x": "[][]int{[]int{0, 1, 2, 3, 4}}"
    }
  },
  {
    "seed": "1652721755011153982",
    "shrunk": {
      "x": "[][]int{[]int{0, 1, 2, 3, 4}}"
    }
  },
  {
    "seed": "1939385193949298751",
    "shrunk": {
      "x": "[][]int{[]int{0}, []int{1, 2, 3, -1}}"
    }
  },
  {
    "seed": "2188306749507764288",
    "shrunk": {
      "x": "[][]int{[]int{0, 1, 2, 3, 4}}"
    }
  },
  {
    "seed": "2460556931035562049",
    "shrunk": {
      "x": "[][]int{[]int{0, 1, 2, 3, 4}}"
    }
  },
  {
    "seed": "2768732237661732930",
    "shrunk": {
      "x": "[][]int{[]int{0, 1, 2, 3, -1}}"
    }
  },
  {
    "seed": "3113618317688963139",
    "shrunk": {
      "x": "[][]int{[]int{0, 1, 2, 3, 4}}"
    }
  },
  {
    "seed": "3422637422180040773",
    "shrunk": {
      "x": "[][]int{[]int{0, 1, 2, 3, 4}}"
    }
  },
  {
    "seed": "3736524996655185989",
    "shrunk": {
      "x": "[][]int{[]int{0, 1, 2, 3, 4}}"
    }
  },
  {
    "seed": "4005647548638298182",
    "shrunk": {
      "x": "[][]int{[]int{0, 1, 2, 3, -1}}"
    }
  },
  {
    "seed": "4343275129640321096",
    "shrunk": {
      "x": "[][]int{[]int{0, 1, 2, 3, 4}}"
    }
  },
  {
    "seed": "4655054888785412168",
    "shrunk": {
      "x": "[][]int{[]int{0, 1, 2, 3, 4}}"
    }
  },
  {
    "seed": "4999836382064017481",
    "shrunk": {
      "x": "[][]int{[]int{0, 1, 2, 3, -1}}"
    }
  },
  {
    "seed": "5271461650145214539",
    "shrunk": {
      "x": "[][]int{[]int{0, 1, 2, 3, 4}}"
    }
  },
  {
    "seed": "5563690851302899787",
    "shrunk": {
      "x": "[][]int{[]int{0, 1, 2, 3, -1}}"
    }
  },
  {
    "seed": "5880661658245791821",
    "shrunk": {
      "x": "[][]int{[]int{0, 1, 2}, []int{3, 4}}"
    }
  },
  {
    "seed": "6202229875491733581",
    "shrunk": {
      "x": "[][]int{[]int{0, 1, 2, 3, 4}}"
    }
  },
  {
    "seed": "6494916825673891919",
    "shrunk": {
      "x": "[][]int{[]int{0, 1, 2, 3, -1}}"
    }
  },
  {
    "seed": "6728306430870290511",
    "shrunk": {
      "x": "[][]int{[]int{0, 1, 2, 3, 4}}"
    }
  },
  {
    "seed": "7050881452874924127",
    "shrunk": {
      "x": "[][]int{[]int{0, 1, 2, 3, -1}}"
    }
  },
  {
    "seed": "7362748451395731538",
    "shrunk": {
      "x": "[][]int{[]int{0, 1, 2, 3, -1}}"
    }
  },
  {
    "seed": "7681659226346750034",
    "shrunk": {
      "x": "[][]int{[]int{0, 1, 2, 3, 4}}"
    }
  },
  {
    "seed": "7970458634125574227",
    "shrunk": {
      "x": "[][]int{[]int{0, 1, 2, 3, 4}}"
    }
  },
  {
    "seed": "8247894791094796372",
    "shrunk": {
      "x": "[][]int{[]int{0, 1, 2, 3, -1}}"
    }
  },
  {
    "seed": "8584958159423012949",
    "shrunk": {
      "x": "[][]int{[]int{0, 1, 2, 3, -1}}"
    }
  },
  {
    "seed": "8896391490800975958",
    "shrunk": {
      "x": "[][]int{[]int{0, 1, 2, 3, 4}}"
    }
  },
  {
    "seed": "9198890332425551960",
    "shrunk": {
      "x": "[][]int{[]int{0, 1, 2, 3, -1}}"
    }
  },
  {
    "seed": "9538883035953365080",
    "shrunk": {
      "x": "[][]int{[]int{0, 1, 2, 3, 4}}"
    }
  },
  {
    "seed": "9808971607685726297",
    "shrunk": {
      "x": "[][]int{[]int{0, 1, 2, 3, 4}}"
    }
  },
  {
    "seed": "10085376457107832922",
    "shrunk": {
      "x": "[][]int{[]int{0, 1, 2, 3, 4}}"
    }
  },
  {
    "seed": "10363777177832390747",
    "shrunk": {
      "x": "[][]int{[]int{0, 1, 2, 3, 4}}"
    }
  },
  {
    "seed": "10643613577274982493",
    "shrunk": {
      "x": "[][]int{[]int{0, 1, 2, 3, 4}}"
    }
  },
  {
    "seed": "10926026742346809440",
    "shrunk": {
      "x": "[][]int{[]int{0, 1, 2, 3, 4}}"
    }
  },
  {
    "seed": "11300599988511309918",
    "shrunk": {
      "x": "[][]int{[]int{0, 1, 2, 3, 4}}"
    }
  },
  {
    "seed": "11573962420539883615",
    "shrunk": {
      "x": "[][]int{[]int{0, 1, 2}, []int{3, -1}}"
    }
  },
  {
    "seed": "11840586121895477344",
    "shrunk": {
      "x": "[][]int{[]int{0, 1, 2, 3, 4}}"
    }
  },
  {
    "seed": "12168643446315155553",
    "shrunk": {
      "x": "[][]int{[]int{0, 1, 2, 3, -1}}"
    }
  },
  {
    "seed": "12414629323007328354",
    "shrunk": {
      "x": "[][]int{[]int{0, 1, 2, 3, 4}}"
    }
  },
  {
    "seed": "12717447778918203491",
    "shrunk": {
      "x": "[][]int{[]int{0}, []int{1, 2, 3, 4}}"
    }
  },
  {
    "seed": "13033227041674100837",
    "shrunk": {
      "x": "[][]int{[]int{0, 1, 2, 3, 4}}"
    }
  }
]